[
    {
        "id": 0,
        "price": "15.50",
        "productName": "Peluche",
        "description": "Un joli petit nounours"
    },
     {
        "id": 1,
        "price": "26",
        "productName": "Licorne",
        "description": "Une superbe licorne rose"
    },
     {
        "id": 2,
        "price": "8.35",
        "productName": "Lunettes de soleil",
        "description": "Une paire de lunettes de soleil rose"
    },
     {
        "id": 3,
        "price": "19.99",
        "productName": "Lot de briquets",
        "description": "Un lot de 7 briquets"
    },
    {
        "id": 4,
        "price": "20.99",
        "productName": "Peluche",
        "description": "Un joli nounours très grand"
    }
]